monocle_reviews-0.3.0.2.dist-info/metadata.json
monocle_reviews-0.3.0.2.dist-info/WHEEL
monocle_reviews-0.3.0.2.dist-info/METADATA
monocle_reviews-0.3.0.2.dist-info/top_level.txt
monocle_reviews-0.3.0.2.dist-info/DESCRIPTION.rst
monocle_reviews-0.3.0.2.dist-info/RECORD
monocle_reviews/__init__.py
monocle_reviews/models.py
monocle_reviews/monocle.py
monocle_reviews/admin.py
monocle_reviews/templates/monocle_reviews/monocle_reviews.html
monocle_reviews/fixtures/monocle_reviews.json
monocle_reviews/fixtures/monocle_reviews/petr.jpg
monocle_reviews/fixtures/monocle_reviews/olga.jpg
monocle_reviews/fixtures/monocle_reviews/mikhail.jpg
monocle_reviews/fixtures/monocle_reviews/georgiy.jpg
monocle_reviews/static/monocle_reviews/monocle_reviews.css
monocle_reviews/static/monocle_reviews/monocle_reviews.js
